src/__init__.py
tests/__init__.py
cool_ocf_project-0.0.4.dist-info/LICENSE
cool_ocf_project-0.0.4.dist-info/METADATA
cool_ocf_project-0.0.4.dist-info/WHEEL
cool_ocf_project-0.0.4.dist-info/top_level.txt
cool_ocf_project-0.0.4.dist-info/RECORD
