Metadata-Version: 2.1
Name: cool-ocf-project
Version: 0.0.4
Summary: Super cool OCF Repo
Author: Jacob Bieker, Jack Kelly, Peter Dudfield
Author-email: info@openclimatefix.org
License: MIT
License-File: LICENSE
Requires-Dist: ocf-blosc2
